keras_spatial/__init__.py
keras_spatial/augmentation.py
keras_spatial/c.py
keras_spatial/dap.py
keras_spatial/datagen.py
keras_spatial/filecache.py
keras_spatial/grid.py
keras_spatial/samples.py
keras_spatial/tiledg.py
keras_spatial/utils.py
keras_spatial-1.0.7.dist-info/AUTHORS.rst
keras_spatial-1.0.7.dist-info/METADATA
keras_spatial-1.0.7.dist-info/WHEEL
keras_spatial-1.0.7.dist-info/entry_points.txt
keras_spatial-1.0.7.dist-info/top_level.txt
keras_spatial-1.0.7.dist-info/RECORD
