Metadata-Version: 2.1
Name: keras-spatial
Version: 1.0.7
Summary: Keras Data Generator class for remote spatial data.
Home-page: https://github.com/IllinoisStateGeologicalSurvey/keras-spatial
Author: Jeff Terstriep
Author-email: jefft@illinois.edu
License: mit
Platform: any
Classifier: Development Status :: 4 - Beta
Classifier: Programming Language :: Python
Classifier: License :: OSI Approved :: University of Illinois/NCSA Open Source License
Classifier: Topic :: Scientific/Engineering :: GIS
Classifier: Topic :: Scientific/Engineering :: Artificial Intelligence
Requires-Dist: scipy
Requires-Dist: rasterio
Requires-Dist: geopandas
Requires-Dist: netCDF4
Provides-Extra: testing
Requires-Dist: pytest ; extra == 'testing'
Requires-Dist: pytest-cov ; extra == 'testing'
